CHANGELOG.md
EorzeaEnv/Data/PlaceName.py
EorzeaEnv/Data/TerritoryWeather.py
EorzeaEnv/Data/Weather.py
EorzeaEnv/Data/WeatherRate.py
EorzeaEnv/Data/__init__.py
EorzeaEnv/__init__.py
EorzeaEnv/eorzea_lang.py
EorzeaEnv/eorzea_place_name.py
EorzeaEnv/eorzea_rainwbow.py
EorzeaEnv/eorzea_time.py
EorzeaEnv/eorzea_weather.py
EorzeaEnv/errors.py
EorzeaEnv/py.typed
LICENSE
README.md
eorzeaenv-2.2.12.dist-info/LICENSE
eorzeaenv-2.2.12.dist-info/METADATA
eorzeaenv-2.2.12.dist-info/WHEEL
eorzeaenv-2.2.12.dist-info/RECORD
