Metadata-Version: 2.1
Name: EorzeaEnv
Version: 2.2.12
Summary: Final Fantasy XIV weather & time tools.
Home-page: https://github.com/EltonChou/EorzeaEnv
License: MIT
Keywords: eorzea,ffxiv,ff14,final fantasy
Author: Elton Chou
Author-email: plscd748@gmail.com
Maintainer: Elton Chou
Maintainer-email: plscd748@gmail.com
Requires-Python: >=3.8,<=3.13
Classifier: Development Status :: 5 - Production/Stable
Classifier: Intended Audience :: Developers
Classifier: License :: OSI Approved :: MIT License
Classifier: Operating System :: OS Independent
Classifier: Programming Language :: Python :: 3
Classifier: Programming Language :: Python :: 3.8
Classifier: Programming Language :: Python :: 3.9
Classifier: Programming Language :: Python :: 3.10
Classifier: Programming Language :: Python :: 3.11
Classifier: Programming Language :: Python :: 3.12
Classifier: Topic :: Utilities
Requires-Dist: numpy (>=1.19.0,<2.0.0) ; python_version >= "3.8" and python_version < "3.12"
Requires-Dist: numpy (>=2.0,<3.0) ; python_version >= "3.12"
Requires-Dist: rapidfuzz (>=2.0.11,<3.0.0)
Project-URL: Bug Reports, https://github.com/EltonChou/EorzeaEnv/issues
Project-URL: Repository, https://github.com/EltonChou/EorzeaEnv
